newsgrabber/__init__.py
newsgrabber/exceptions.py
newsgrabber/network_manager.py
newsgrabber/parser.py
newsgrabber/utils.py
newsgrabber/models/__init__.py
newsgrabber/models/news_url.py
newsgrabber-24.1.2.dist-info/LICENSE
newsgrabber-24.1.2.dist-info/METADATA
newsgrabber-24.1.2.dist-info/WHEEL
newsgrabber-24.1.2.dist-info/top_level.txt
newsgrabber-24.1.2.dist-info/RECORD
