Metadata-Version: 2.1
Name: newsgrabber
Version: 24.1.2
Summary: Google News Sitemap Parser
Author-email: Ahmet Yiğit Budak <yibudak@gmail.com>
Maintainer-email: Ahmet Yiğit Budak <yibudak@gmail.com>
License:                     GNU AFFERO GENERAL PUBLIC LICENSE
Project-URL: Homepage, https://github.com/yibudak/newsgrabber
Project-URL: Bug Reports, https://github.com/yibudak/newsgrabber/issues
Project-URL: Source, https://github.com/yibudak/newsgrabber
Keywords: sitemap,google news,parser
Classifier: Development Status :: 4 - Beta
Classifier: Intended Audience :: Developers
Classifier: Intended Audience :: Information Technology
Classifier: License :: OSI Approved :: GNU Affero General Public License v3
Classifier: Programming Language :: Python
Classifier: Operating System :: OS Independent
Classifier: Programming Language :: Python :: 3.11
Classifier: Programming Language :: Python :: 3.12
Classifier: Programming Language :: Python :: 3.13
Classifier: Programming Language :: Python :: 3 :: Only
Classifier: Programming Language :: Python :: Implementation :: PyPy
Classifier: Topic :: Internet :: WWW/HTTP :: Indexing/Search
Classifier: Topic :: Text Processing :: Indexing
Classifier: Topic :: Text Processing :: Markup :: XML
Requires-Python: >=3.11
License-File: LICENSE
Requires-Dist: lxml
Requires-Dist: requests
Requires-Dist: python-dateutil
Provides-Extra: dev
Requires-Dist: check-manifest; extra == "dev"
Provides-Extra: test
Requires-Dist: coverage; extra == "test"
